Metadata-Version: 2.4
Name: adafruit-circuitpython-acep7in
Version: 1.0.3
Summary: Driver for 7.3" 7-color (aka ACeP) epaper display
Author-email: Adafruit Industries <circuitpython@adafruit.com>
License: MIT
Project-URL: Homepage, https://github.com/adafruit/Adafruit_CircuitPython_ACeP7in
Keywords: adafruit,blinka,circuitpython,micropython,acep7in,epd,acep
Classifier: Intended Audience :: Developers
Classifier: Topic :: Software Development :: Libraries
Classifier: Topic :: Software Development :: Embedded Systems
Classifier: Topic :: System :: Hardware
Classifier: License :: OSI Approved :: MIT License
Classifier: Programming Language :: Python :: 3
License-File: LICENSE
Requires-Dist: Adafruit-Blinka
Requires-Dist: Adafruit-Blinka-displayio
Provides-Extra: optional
Dynamic: license-file
